tibvh/__init__.py
tibvh/geometry/__init__.py
tibvh/geometry/aabb_generator.py
tibvh/geometry/geom_intersection.py
tibvh/geometry/utils.py
tibvh/lbvh/__init__.py
tibvh/lbvh/aabb.py
tibvh/lbvh/lbvh.py
tibvh-0.1.2.dist-info/licenses/LICENSE
tibvh-0.1.2.dist-info/METADATA
tibvh-0.1.2.dist-info/WHEEL
tibvh-0.1.2.dist-info/top_level.txt
tibvh-0.1.2.dist-info/RECORD
