Metadata-Version: 2.4
Name: tibvh
Version: 0.1.2
Summary: A high-performance Taichi-based Linear BVH implementation for 3D geometry processing
Author-email: TIBVH Contributors <contributors@example.com>
Maintainer-email: TIBVH Contributors <contributors@example.com>
License: MIT License
Project-URL: homepage, https://github.com/yourorg/tibvh
Project-URL: documentation, https://tibvh.readthedocs.io
Project-URL: repository, https://github.com/yourorg/tibvh
Project-URL: Bug Tracker, https://github.com/yourorg/tibvh/issues
Keywords: bvh,taichi,geometry,3d,ray-tracing,spatial-data-structures,collision-detection,computer-graphics
Classifier: Development Status :: 3 - Alpha
Classifier: Intended Audience :: Developers
Classifier: Intended Audience :: Science/Research
Classifier: License :: OSI Approved :: MIT License
Classifier: Operating System :: OS Independent
Classifier: Programming Language :: Python :: 3
Classifier: Programming Language :: Python :: 3.8
Classifier: Programming Language :: Python :: 3.9
Classifier: Programming Language :: Python :: 3.10
Classifier: Programming Language :: Python :: 3.11
Classifier: Programming Language :: Python :: 3.12
Classifier: Topic :: Scientific/Engineering
Classifier: Topic :: Software Development :: Libraries :: Python Modules
Classifier: Topic :: Multimedia :: Graphics :: 3D Modeling
Classifier: Topic :: Multimedia :: Graphics :: 3D Rendering
Requires-Python: >=3.8
License-File: LICENSE
Requires-Dist: taichi>=1.6.0
Requires-Dist: numpy>=1.19.0
Requires-Dist: torch>=1.10.0
Provides-Extra: dev
Requires-Dist: pytest>=6.0; extra == "dev"
Requires-Dist: pytest-cov>=2.0; extra == "dev"
Requires-Dist: black>=22.0; extra == "dev"
Requires-Dist: isort>=5.0; extra == "dev"
Requires-Dist: flake8>=4.0; extra == "dev"
Requires-Dist: mypy>=0.910; extra == "dev"
Requires-Dist: pre-commit>=2.15.0; extra == "dev"
Provides-Extra: docs
Requires-Dist: sphinx>=4.0; extra == "docs"
Requires-Dist: sphinx-rtd-theme>=1.0; extra == "docs"
Requires-Dist: myst-parser>=0.17.0; extra == "docs"
Provides-Extra: examples
Requires-Dist: matplotlib>=3.0; extra == "examples"
Requires-Dist: jupyter>=1.0; extra == "examples"
Dynamic: license-file
